scripts/__init__.py
scripts/download_models.py
scripts/start.py
smartresume/__init__.py
smartresume/backend/__init__.py
smartresume/backend/resume_analyzer.py
smartresume/cli/__init__.py
smartresume/cli/models_download.py
smartresume/cli/vllm_server.py
smartresume/data/__init__.py
smartresume/data/data_processor.py
smartresume/data/file_processor.py
smartresume/data/layout_detector.py
smartresume/data/ocr_provider.py
smartresume/data/text_extractor.py
smartresume/model/__init__.py
smartresume/model/llm_client.py
smartresume/utils/__init__.py
smartresume/utils/config.py
smartresume/utils/model_paths.py
smartresume/utils/models_download_utils.py
smartresume/utils/prompts.py
smartresume-0.1.1.dist-info/licenses/LICENSE
smartresume-0.1.1.dist-info/METADATA
smartresume-0.1.1.dist-info/WHEEL
smartresume-0.1.1.dist-info/entry_points.txt
smartresume-0.1.1.dist-info/top_level.txt
smartresume-0.1.1.dist-info/RECORD
