Metadata-Version: 2.4
Name: SmartResume
Version: 0.1.1
Summary: Intelligent Resume Parsing System
License: Apache-2.0
Project-URL: Homepage, https://github.com/alibaba/SmartResume
Project-URL: Repository, https://github.com/alibaba/SmartResume
Project-URL: Documentation, https://github.com/alibaba/SmartResume#readme
Project-URL: Bug Tracker, https://github.com/alibaba/SmartResume/issues
Keywords: resume,parsing,ocr,llm,pdf,layout
Classifier: Programming Language :: Python :: 3.9
Classifier: Programming Language :: Python :: 3.10
Classifier: Programming Language :: Python :: 3.11
Classifier: Programming Language :: Python :: 3.12
Classifier: Programming Language :: Python :: 3.13
Requires-Python: >=3.9
License-File: LICENSE
Requires-Dist: numpy>=1.23
Requires-Dist: pillow>=9.5
Requires-Dist: opencv-python>=4.7
Requires-Dist: pdfplumber>=0.10.0
Requires-Dist: pyyaml>=6.0
Requires-Dist: tiktoken>=0.5.1
Requires-Dist: openai>=1.30.0
Requires-Dist: json-repair>=0.16.0
Requires-Dist: easyocr>=1.7.0
Requires-Dist: langdetect>=1.0.9
Requires-Dist: vllm>=0.2.0
Requires-Dist: torch>=2.0.0
Requires-Dist: transformers>=4.30.0
Requires-Dist: accelerate>=0.20.0
Requires-Dist: modelscope>=1.9.0
Requires-Dist: requests>=2.25.0
Requires-Dist: onnxruntime>=1.17.0
Provides-Extra: dev
Requires-Dist: pytest>=7.0; extra == "dev"
Requires-Dist: pytest-cov>=4.0; extra == "dev"
Requires-Dist: black>=23.0; extra == "dev"
Requires-Dist: flake8>=6.0; extra == "dev"
Requires-Dist: mypy>=1.0; extra == "dev"
Provides-Extra: docs
Requires-Dist: sphinx>=5.0; extra == "docs"
Requires-Dist: sphinx-rtd-theme>=1.0; extra == "docs"
Provides-Extra: gradio
Requires-Dist: gradio<6,>=5.34; extra == "gradio"
Requires-Dist: gradio-pdf>=0.0.22; extra == "gradio"
Dynamic: license-file
